brainglobe_template_builder/__init__.py
brainglobe_template_builder/io.py
brainglobe_template_builder/plots.py
brainglobe_template_builder/preprocess.py
brainglobe_template_builder/standardise.py
brainglobe_template_builder/validate.py
brainglobe_template_builder/napari/__init__.py
brainglobe_template_builder/napari/_reader.py
brainglobe_template_builder/napari/_widget.py
brainglobe_template_builder/napari/align_widget.py
brainglobe_template_builder/napari/mask_widget.py
brainglobe_template_builder/napari/napari.yaml
brainglobe_template_builder/napari/reorient_widget.py
brainglobe_template_builder/napari/save_widget.py
brainglobe_template_builder/napari/utils.py
brainglobe_template_builder/utils/__init__.py
brainglobe_template_builder/utils/alignment.py
brainglobe_template_builder/utils/annotation_filter.py
brainglobe_template_builder/utils/brightness.py
brainglobe_template_builder/utils/cropping.py
brainglobe_template_builder/utils/masking.py
brainglobe_template_builder/utils/preproc_config.py
brainglobe_template_builder/utils/splitting.py
brainglobe_template_builder/utils/transform_utils.py
brainglobe_template_builder/utils/wingdisc_utils.py
brainglobe_template_builder-0.1.1.dist-info/licenses/LICENSE
brainglobe_template_builder-0.1.1.dist-info/METADATA
brainglobe_template_builder-0.1.1.dist-info/WHEEL
brainglobe_template_builder-0.1.1.dist-info/entry_points.txt
brainglobe_template_builder-0.1.1.dist-info/top_level.txt
brainglobe_template_builder-0.1.1.dist-info/RECORD
