Metadata-Version: 2.4
Name: brainglobe-template-builder
Version: 0.1.1
Summary: Build unbiased anatomical templates from individual images
Author-email: Niko Sirmpilatze <niko.sirbiladze@gmail.com>
License: BSD-3-Clause
Project-URL: Homepage, https://github.com/brainglobe/brainglobe-template-builder
Project-URL: Bug Tracker, https://github.com/brainglobe/brainglobe-template-builder/issues
Project-URL: Documentation, https://brainglobe.github.io/brainglobe-template-builder
Project-URL: Source Code, https://github.com/brainglobe/brainglobe-template-builder
Project-URL: User Support, https://github.com/brainglobe/brainglobe-template-builder/issues
Classifier: Development Status :: 2 - Pre-Alpha
Classifier: Programming Language :: Python
Classifier: Programming Language :: Python :: 3
Classifier: Programming Language :: Python :: 3.11
Classifier: Programming Language :: Python :: 3.12
Classifier: Programming Language :: Python :: 3.13
Classifier: Operating System :: OS Independent
Classifier: License :: OSI Approved :: BSD License
Requires-Python: >=3.11.0
License-File: LICENSE
Requires-Dist: napari[all]>=0.6.1
Requires-Dist: brainglobe-utils>=0.9.0
Requires-Dist: brainglobe-atlasapi>=2.0.7
Requires-Dist: napari-itk-io
Requires-Dist: loguru
Requires-Dist: antspyx
Requires-Dist: qt-niu
Requires-Dist: pydantic
Requires-Dist: simpleitk
Requires-Dist: fancylog[git]
Provides-Extra: dev
Requires-Dist: pytest; extra == "dev"
Requires-Dist: pytest-cov; extra == "dev"
Requires-Dist: pytest-mock; extra == "dev"
Requires-Dist: coverage; extra == "dev"
Requires-Dist: tox; extra == "dev"
Requires-Dist: black; extra == "dev"
Requires-Dist: mypy; extra == "dev"
Requires-Dist: pre-commit; extra == "dev"
Requires-Dist: ruff; extra == "dev"
Requires-Dist: setuptools_scm; extra == "dev"
Requires-Dist: pooch; extra == "dev"
Requires-Dist: types-PyYAML; extra == "dev"
Provides-Extra: wingdisc
Requires-Dist: bioio; extra == "wingdisc"
Requires-Dist: bioio_czi; extra == "wingdisc"
Requires-Dist: bioio_sldy; extra == "wingdisc"
Dynamic: license-file
